{
  "name": "Kin Lane - Link",
  "description": "This is my default link API, using it to manage the links I use across the API Evangelist network.",
  "image": "https://s3.amazonaws.com/kinlane-productions/bw-icons/bw-link.png",
  "tags": [
    "Application Programming Interface",
    "API",
    "Link"
  ],
  "created": "2014-04-07",
  "modified": "2015-04-11",
  "url": "https://kin-lane.github.io/link/apis.json",
  "SpecificationVersion": "0.14",
  "apis": [
    {
      "name": "Link",
      "description": "A link API resource.",
      "image": "https://s3.amazonaws.com/kinlane-productions/bw-icons/bw-link.png",
      "humanURL": "https://kin-lane.github.io/link/",
      "baseURL": "http://link.api.kinlane.com",
      "tags": [
        "API",
        "Application Programming Interface",
        "Link"
      ],
      "properties": [
        {
          "type": "Swagger",
          "url": "https://kin-lane.github.io/link/swagger.json"
        },
        {
          "type": "x-postman",
          "url": "https://kin-lane.github.io/link/postman.json"
        },
        {
          "type": "x-apimatic-sdks",
          "url": "https://kin-lane.github.io/link/code/"
        },
        {
          "type": "x-api-science",
          "url": "https://kin-lane.github.io/link/status/"
        }
      ],
      "contact": [
        {
          "FN": "API Evangelist",
          "email": "info@apievangelist.com",
          "X-twitter": "apievangelist"
        }
      ]
    }
  ],
  "include": [
    {
      "name": "API API (Inception)",
      "url": "https://kin-lane.github.io/api/apis.json"
    },
    {
      "name": "Audio API",
      "url": "https://kin-lane.github.io/audio/apis.json"
    },
    {
      "name": "Comment API",
      "url": "https://kin-lane.github.io/comment/apis.json"
    },
    {
      "name": "Curated API",
      "url": "https://kin-lane.github.io/curated/apis.json"
    },
    {
      "name": "Glossary API",
      "url": "https://kin-lane.github.io/glossary/apis.json"
    },
    {
      "name": "Image API",
      "url": "https://kin-lane.github.io/image/apis.json"
    },
    {
      "name": "Job API",
      "url": "https://kin-lane.github.io/job/apis.json"
    },
    {
      "name": "Link API",
      "url": "https://kin-lane.github.io/link/apis.json"
    },
    {
      "name": "Note API",
      "url": "https://kin-lane.github.io/note/apis.json"
    },
    {
      "name": "Organization API",
      "url": "https://kin-lane.github.io/organization/apis.json"
    },
    {
      "name": "Page API",
      "url": "https://kin-lane.github.io/page/apis.json"
    },
    {
      "name": "Patent API",
      "url": "https://kin-lane.github.io/patent/apis.json"
    },
    {
      "name": "People API",
      "url": "https://kin-lane.github.io/people/apis.json"
    },
    {
      "name": "Project API",
      "url": "https://kin-lane.github.io/project/apis.json"
    },
    {
      "name": "Tag API",
      "url": "https://kin-lane.github.io/tag/apis.json"
    },
    {
      "name": "Tool API",
      "url": "https://kin-lane.github.io/tool/apis.json"
    },
    {
      "name": "Video API",
      "url": "https://kin-lane.github.io/video/apis.json"
    }
  ],
  "maintainers": [
    {
      "FN": "API Evangliest",
      "X-twitter": "apievangelist",
      "email": "info@apievangelist.com"
    }
  ]
}
